Workbook

Sheet Assumptions
C3: ChemBalance Seed Assumptions
C5: Management scenario inputs; replace blue cells with actual operating data.
C6: USD in $000 except prices and percentages
C8: Metric | D8: 2027E | E8: 2028E | F8: 2029E
C9: New Pro subscriptions | D9: 180 | E9: 600 | F9: 1400
C10: New Team accounts | D10: 6 | E10: 20 | F10: 45
C11: New Enterprise accounts | D11: 1 | E11: 4 | F11: 10
C12: Pro annual price ($) | D12: 180 | E12: 180 | F12: 180
C13: Team annual contract value ($) | D13: 1500 | E13: 1500 | F13: 1500
C14: Enterprise annual contract value ($) | D14: 7500 | E14: 7500 | F14: 7500
C15: Cost of revenue (% of revenue) | D15: 0.09 | E15: 0.09 | F15: 0.09
C16: Research & development ($000) | D16: 210 | E16: 280 | F16: 350
C17: Sales & marketing ($000) | D17: 90 | E17: 150 | F17: 240
C18: General & administrative ($000) | D18: 70 | E18: 95 | F18: 130
C19: Working capital / tools ($000) | D19: 20 | E19: 30 | F19: 40
C20: Seed capital proceeds ($000) | D20: 1350 | E20: 0 | F20: 0
C22: Unit economics targets
C23: Segment | D23: ACV ($) | E23: Gross margin | F23: Annual churn | G23: CAC ($) | H23: LTV / CAC
C24: Pro | D24: 180 | E24: 0.91 | F24: 0.25 | G24: 90 | H24: =D24*E24/F24/G24
C25: Team | D25: 1500 | E25: 0.91 | F25: 0.12 | G25: 900 | H25: =D25*E25/F25/G25
C26: Enterprise | D26: 7500 | E26: 0.91 | F26: 0.08 | G26: 5000 | H26: =D26*E26/F26/G26

Sheet Revenue Build
C3: ChemBalance Revenue Build
C5: Subscription revenue uses average active accounts for each forecast year.
C6: USD in $000 except account counts and annual contract values
C8: Metric | D8: 2027E | E8: 2028E | F8: 2029E
C9: Pro subscriptions
C10: Beginning accounts | D10: =0 | E10: =D12 | F10: =E12
C11: New accounts | D11: =Assumptions!D9 | E11: =Assumptions!E9 | F11: =Assumptions!F9
C12: Ending accounts | D12: =D10+D11 | E12: =E10+E11 | F12: =F10+F11
C13: Average accounts | D13: =(D10+D12)/2 | E13: =(E10+E12)/2 | F13: =(F10+F12)/2
C14: Annual contract value ($) | D14: =Assumptions!D12 | E14: =Assumptions!E12 | F14: =Assumptions!F12
C15: Revenue ($000) | D15: =D13*D14/1000 | E15: =E13*E14/1000 | F15: =F13*F14/1000
C18: Team accounts
C19: Beginning accounts | D19: =0 | E19: =D21 | F19: =E21
C20: New accounts | D20: =Assumptions!D10 | E20: =Assumptions!E10 | F20: =Assumptions!F10
C21: Ending accounts | D21: =D19+D20 | E21: =E19+E20 | F21: =F19+F20
C22: Average accounts | D22: =(D19+D21)/2 | E22: =(E19+E21)/2 | F22: =(F19+F21)/2
C23: Annual contract value ($) | D23: =Assumptions!D13 | E23: =Assumptions!E13 | F23: =Assumptions!F13
C24: Revenue ($000) | D24: =D22*D23/1000 | E24: =E22*E23/1000 | F24: =F22*F23/1000
C27: Enterprise accounts
C28: Beginning accounts | D28: =0 | E28: =D30 | F28: =E30
C29: New accounts | D29: =Assumptions!D11 | E29: =Assumptions!E11 | F29: =Assumptions!F11
C30: Ending accounts | D30: =D28+D29 | E30: =E28+E29 | F30: =F28+F29
C31: Average accounts | D31: =(D28+D30)/2 | E31: =(E28+E30)/2 | F31: =(F28+F30)/2
C32: Annual contract value ($) | D32: =Assumptions!D14 | E32: =Assumptions!E14 | F32: =Assumptions!F14
C33: Revenue ($000) | D33: =D31*D32/1000 | E33: =E31*E32/1000 | F33: =F31*F32/1000
C36: Revenue summary
C37: Total revenue ($000) | D37: =D15+D24+D33 | E37: =E15+E24+E33 | F37: =F15+F24+F33

Sheet P&L & Cash
C3: ChemBalance Profit & Loss and Cash
C5: Base-case cash plan funded by the Seed raise; no income tax benefit is modeled while loss-making.
C6: USD in $000
C8: Metric | D8: 2027E | E8: 2028E | F8: 2029E
C9: Revenue | D9: ='Revenue Build'!D37 | E9: ='Revenue Build'!E37 | F9: ='Revenue Build'!F37
C10: Cost of revenue | D10: =-D9*Assumptions!D15 | E10: =-E9*Assumptions!E15 | F10: =-F9*Assumptions!F15
C11: Gross profit | D11: =D9+D10 | E11: =E9+E10 | F11: =F9+F10
C12: Gross margin | D12: =D11/D9 | E12: =E11/E9 | F12: =F11/F9
C14: Research & development | D14: =-Assumptions!D16 | E14: =-Assumptions!E16 | F14: =-Assumptions!F16
C15: Sales & marketing | D15: =-Assumptions!D17 | E15: =-Assumptions!E17 | F15: =-Assumptions!F17
C16: General & administrative | D16: =-Assumptions!D18 | E16: =-Assumptions!E18 | F16: =-Assumptions!F18
C17: EBITDA | D17: =SUM(D11:D16) | E17: =SUM(E11:E16) | F17: =SUM(F11:F16)
C18: EBITDA margin | D18: =D17/D9 | E18: =E17/E9 | F18: =F17/F9
C20: Working capital / tools | D20: =-Assumptions!D19 | E20: =-Assumptions!E19 | F20: =-Assumptions!F19
C21: Free cash flow | D21: =D17+D20 | E21: =E17+E20 | F21: =F17+F20
C23: Seed capital proceeds | D23: =Assumptions!D20 | E23: =Assumptions!E20 | F23: =Assumptions!F20
C24: Beginning cash | D24: =0 | E24: =D25 | F24: =E25
C25: Ending cash | D25: =D24+D21+D23 | E25: =E24+E21+E23 | F25: =F24+F21+F23

Sheet Scenarios
C3: ChemBalance Seed Scenario Summary
C5: Illustrative sensitivity of 2029 revenue and ending cash to new-logo acquisition pace.
C6: USD in $000 except percentages
C8: Scenario | D8: New-logo multiplier | E8: 2029 revenue | F8: 2029 ending cash | G8: Interpretation
C9: Downside | D9: 0.7 | E9: ='Revenue Build'!F37*D9 | F9: ='P&L & Cash'!F25+('Revenue Build'!F37*D9-'Revenue Build'!F37)*0.91 | G9: Slower conversion or longer institutional sales cycle
C10: Base | D10: 1 | E10: ='Revenue Build'!F37*D10 | F10: ='P&L & Cash'!F25+('Revenue Build'!F37*D10-'Revenue Build'!F37)*0.91 | G10: Management operating plan
C11: Upside | D11: 1.3 | E11: ='Revenue Build'!F37*D11 | F11: ='P&L & Cash'!F25+('Revenue Build'!F37*D11-'Revenue Build'!F37)*0.91 | G11: Faster distribution or partner-assisted growth
C14: Scenario interpretation
C15: The downside / base / upside cases vary only customer acquisition. Product costs, headcount, and pricing remain at base assumptions so decision-makers can see commercial sensitivity clearly.

Sheet Use of Funds
C3: ChemBalance Seed Use of Funds
C5: Proposed allocation of the Seed raise; management must align spending gates with demonstrated milestones.
C6: USD in $000
C8: Workstream | D8: % of Seed | E8: Amount | F8: Purpose and release gate
C9: Product & engineering | D9: 0.45 | E9: =Assumptions!D20*D9 | F9: Stabilize multi-platform distribution; build percentage analysis and stoichiometry workspace.
C10: Go-to-market & customer success | D10: 0.25 | E10: =Assumptions!D20*D10 | F10: Run structured pilots, content-led acquisition, onboarding, and partner distribution experiments.
C11: Operations & administration | D11: 0.15 | E11: =Assumptions!D20*D11 | F11: Legal setup, finance, support operations, compliance and essential tools.
C12: Security & distribution trust | D12: 0.1 | E12: =Assumptions!D20*D12 | F12: Code-signing, macOS notarization, release integrity and production support.
C13: Contingency reserve | D13: 0.05 | E13: =Assumptions!D20*D13 | F13: Protect the plan against delayed conversion or platform certification work.
C15: Total Seed capital | D15: =SUM(D9:D13) | E15: =SUM(E9:E13)

Sheet Checks
C3: ChemBalance Seed Model Checks
C5: Formula checks; the model must be reviewed in Excel after all management inputs are updated.
C6: USD in $000 unless stated
C8: Check | D8: Value | E8: Interpretation
C9: Use of funds equals Seed proceeds | D9: ='Use of Funds'!E15-Assumptions!D20 | E9: Pass when 0.0
C10: Base 2029 ending cash | D10: ='P&L & Cash'!F25 | E10: Positive indicates cash coverage through 2029 under base assumptions
C11: 2029 revenue growth vs. 2028 | D11: ='P&L & Cash'!F9/'P&L & Cash'!E9-1 | E11: Review whether the implied sales ramp is supported by pilots and channel data
C12: 2029 gross margin | D12: ='P&L & Cash'!F12 | E12: Derived from cost-of-revenue assumption
